[
  {
    "year": 2004,
    "where": "Chateau d'Oex",
    "start": "2004-09-17",
    "end": "2004-09-20",
    "remarks": "",
    "isCDO": true,
    "members": [
      1,
      2,
      3,
      4,
      5,
      8,
      9,
      10,
      11,
      13,
      15,
      17,
      18
    ],
    "guests": []
  },
  {
    "year": 2005,
    "where": "Chateau d'Oex",
    "start": "2005-09-16",
    "end": "2005-09-19",
    "remarks": "",
    "isCDO": true,
    "members": [
      1,
      2,
      3,
      4,
      5,
      8,
      9,
      10,
      11,
      12,
      13,
      15,
      16,
      17,
      18,
      19,
      23
    ],
    "guests": []
  },
  {
    "year": 2006,
    "where": "Chateau d'Oex",
    "start": "2006-05-25",
    "end": "2006-05-28",
    "remarks": "",
    "isCDO": true,
    "members": [
      1,
      3,
      4,
      5,
      8,
      10,
      11,
      12,
      15,
      16,
      17,
      18,
      19
    ],
    "guests": [
      "Carole"
    ]
  },
  {
    "year": 2007,
    "where": "Chateau d'Oex",
    "start": "2007-09-14",
    "end": "2007-09-17",
    "remarks": "",
    "isCDO": true,
    "members": [
      1,
      2,
      3,
      4,
      5,
      8,
      9,
      10,
      12,
      13,
      15,
      16,
      17,
      19,
      23
    ],
    "guests": [
      "Carole"
    ]
  },
  {
    "year": 2008,
    "where": "Chateau d'Oex",
    "start": "2008-05-01",
    "end": "2008-05-04",
    "remarks": "",
    "isCDO": true,
    "members": [
      1,
      3,
      4,
      5,
      8,
      9,
      10,
      11,
      12,
      15,
      16,
      17,
      19,
      20,
      23
    ],
    "guests": []
  },
  {
    "year": 2008,
    "where": "Vallée de Joux",
    "start": "2008-07-11",
    "end": "2008-07-15",
    "remarks": "5 ans LKT",
    "isCDO": false,
    "members": [
      1,
      2,
      3,
      5,
      8,
      10,
      12,
      13,
      16,
      17,
      20,
      23
    ],
    "guests": []
  },
  {
    "year": 2009,
    "where": "Chateau d'Oex",
    "start": "2009-05-20",
    "end": "2009-05-24",
    "remarks": "",
    "isCDO": true,
    "members": [
      1,
      3,
      4,
      5,
      8,
      9,
      10,
      11,
      12,
      13,
      17,
      19,
      20,
      23
    ],
    "guests": [
      "Sblanc",
      "Zogzog"
    ]
  },
  {
    "year": 2009,
    "where": "Vallée de Joux",
    "start": "2009-09-21",
    "end": "2009-09-24",
    "remarks": "",
    "isCDO": false,
    "members": [
      1,
      3,
      5,
      8,
      10,
      11,
      12,
      13,
      20
    ],
    "guests": []
  },
  {
    "year": 2010,
    "where": "Chateau d'Oex",
    "start": "2010-11-05",
    "end": "2010-11-07",
    "remarks": "",
    "isCDO": true,
    "members": [
      1,
      3,
      4,
      5,
      8,
      9,
      10,
      11,
      12,
      13,
      15,
      17,
      20,
      23
    ],
    "guests": []
  },
  {
    "year": 2011,
    "where": "Chateau d'Oex",
    "start": "2011-06-02",
    "end": "2011-06-05",
    "remarks": "",
    "isCDO": true,
    "members": [
      1,
      4,
      5,
      9,
      11,
      12,
      13,
      17,
      19,
      20,
      23
    ],
    "guests": []
  },
  {
    "year": 2012,
    "where": "Chateau d'Oex",
    "start": "2012-05-16",
    "end": "2012-05-20",
    "remarks": "",
    "isCDO": true,
    "members": [
      1,
      2,
      3,
      4,
      5,
      8,
      9,
      10,
      11,
      12,
      13,
      16,
      17,
      19,
      20,
      23
    ],
    "guests": []
  },
  {
    "year": 2012,
    "where": "Vallée de Joux",
    "start": "2012-09-14",
    "end": "2012-09-16",
    "remarks": "",
    "isCDO": false,
    "members": [
      1,
      3,
      4,
      5,
      8,
      9,
      10,
      11,
      12,
      13,
      16,
      17,
      20,
      23
    ],
    "guests": []
  },
  {
    "year": 2013,
    "where": "Chateau d'Oex",
    "start": "2013-05-08",
    "end": "2013-05-12",
    "remarks": "Gourdin qu'un soir",
    "isCDO": true,
    "members": [
      1,
      3,
      4,
      5,
      8,
      9,
      10,
      11,
      12,
      13,
      16,
      17,
      19,
      20,
      21,
      23
    ],
    "guests": []
  },
  {
    "year": 2013,
    "where": "Bruxelles",
    "start": "2013-10-04",
    "end": "2013-10-04",
    "remarks": "10 ans LKT",
    "isCDO": false,
    "members": [
      1,
      2,
      3,
      5,
      8,
      9,
      10,
      11,
      12,
      16,
      17,
      19,
      20,
      23
    ],
    "guests": []
  },
  {
    "year": 2014,
    "where": "Chateau d'Oex",
    "start": "2014-05-28",
    "end": "2014-06-01",
    "remarks": "Gourdin qu'un soir",
    "isCDO": true,
    "members": [
      1,
      2,
      4,
      5,
      9,
      10,
      11,
      12,
      13,
      16,
      17,
      19,
      20,
      21,
      23
    ],
    "guests": []
  },
  {
    "year": 2015,
    "where": "Chateau d'Oex",
    "start": "2015-05-13",
    "end": "2015-05-17",
    "remarks": "Gourdin qu'un soir",
    "isCDO": true,
    "members": [
      1,
      2,
      3,
      4,
      5,
      8,
      9,
      10,
      11,
      12,
      13,
      17,
      19,
      20,
      21,
      23
    ],
    "guests": []
  },
  {
    "year": 2015,
    "where": "Vallée de Joux",
    "start": "2015-09-11",
    "end": "2015-09-13",
    "remarks": "",
    "isCDO": false,
    "members": [
      1,
      3,
      5,
      8,
      9,
      10,
      11,
      12,
      16,
      17,
      20,
      21
    ],
    "guests": []
  },
  {
    "year": 2016,
    "where": "Chateau d'Oex",
    "start": "2016-05-04",
    "end": "2016-05-08",
    "remarks": "Vass et Gourdin qu'un soir",
    "isCDO": true,
    "members": [
      2,
      3,
      4,
      5,
      8,
      9,
      10,
      11,
      12,
      13,
      15,
      16,
      17,
      19,
      20,
      21,
      23
    ],
    "guests": [
      "Tiago"
    ]
  },
  {
    "year": 2017,
    "where": "Chateau d'Oex",
    "start": "2017-05-24",
    "end": "2017-05-28",
    "remarks": "Sam un soir",
    "isCDO": true,
    "members": [
      1,
      2,
      3,
      4,
      5,
      8,
      9,
      10,
      11,
      12,
      16,
      17,
      19,
      20,
      21,
      22,
      23
    ],
    "guests": [
      "Manu2"
    ]
  },
  {
    "year": 2018,
    "where": "Chateau d'Oex",
    "start": "2018-05-09",
    "end": "2018-05-13",
    "remarks": "",
    "isCDO": true,
    "members": [
      1,
      2,
      3,
      5,
      8,
      9,
      11,
      12,
      16,
      17,
      19,
      20,
      22,
      23
    ],
    "guests": []
  },
  {
    "year": 2019,
    "where": "Chateau d'Oex",
    "start": "2019-05-29",
    "end": "2019-06-02",
    "remarks": "",
    "isCDO": true,
    "members": [
      1,
      2,
      3,
      5,
      8,
      9,
      10,
      11,
      12,
      16,
      17,
      19,
      20,
      21,
      23
    ],
    "guests": []
  },
  {
    "year": 2020,
    "where": "Chateau d'Oex",
    "start": "2020-10-09",
    "end": "2020-10-11",
    "remarks": "Lui et Groumpf qu'un soir, LeGroudin un jour",
    "isCDO": true,
    "members": [
      1,
      3,
      5,
      9,
      10,
      11,
      12,
      16,
      17,
      19,
      20,
      21,
      22
    ],
    "guests": []
  },
  {
    "year": 2021,
    "where": "Chamoson",
    "start": "2021-05-14",
    "end": "2021-05-16",
    "remarks": "Covid",
    "isCDO": false,
    "members": [
      2,
      5,
      9,
      10,
      11,
      12,
      16,
      20,
      21,
      22
    ],
    "guests": []
  },
  {
    "year": 2021,
    "where": "Chateau d'Oex",
    "start": "2021-10-15",
    "end": "2021-10-17",
    "remarks": "Sblarfei qu'un jour",
    "isCDO": true,
    "members": [
      1,
      2,
      3,
      5,
      8,
      9,
      10,
      11,
      12,
      16,
      17,
      21
    ],
    "guests": []
  },
  {
    "year": 2022,
    "where": "Chateau d'Oex",
    "start": "2022-05-22",
    "end": "2022-05-26",
    "remarks": "Sblarfei qu'un jour",
    "isCDO": true,
    "members": [
      1,
      2,
      3,
      5,
      8,
      9,
      10,
      11,
      12,
      16,
      17,
      19,
      21,
      22,
      23
    ],
    "guests": []
  },
  {
    "year": 2023,
    "where": "Chateau d'Oex",
    "start": "2023-05-17",
    "end": "2023-05-21",
    "remarks": "Lui qu'un jour",
    "isCDO": true,
    "members": [
      1,
      3,
      5,
      8,
      9,
      10,
      11,
      12,
      16,
      17,
      19,
      20,
      21,
      22,
      23
    ],
    "guests": []
  },
  {
    "year": 2023,
    "where": "Dijon",
    "start": "2023-09-29",
    "end": "2023-10-01",
    "remarks": "20 ans LKT",
    "isCDO": false,
    "members": [
      1,
      2,
      3,
      5,
      8,
      9,
      10,
      11,
      12,
      16,
      17,
      20,
      21,
      22
    ],
    "guests": []
  },
  {
    "year": 2024,
    "where": "Chateau d'Oex",
    "start": "2024-05-08",
    "end": "2024-05-12",
    "remarks": "",
    "isCDO": true,
    "members": [
      2,
      3,
      5,
      8,
      9,
      10,
      11,
      12,
      16,
      17,
      20,
      21,
      23
    ],
    "guests": [
      "Sablas"
    ]
  },
  {
    "year": 2025,
    "where": "Chateau d'Oex",
    "start": "2025-05-28",
    "end": "2025-06-01",
    "remarks": "",
    "isCDO": true,
    "members": [
      1,
      3,
      5,
      8,
      9,
      10,
      11,
      12,
      16,
      17,
      19,
      20,
      21,
      22,
      23
    ],
    "guests": []
  },
  {
    "year": 2026,
    "where": "Chateau d'Oex",
    "start": "2026-05-13",
    "end": "2026-05-17",
    "remarks": "Julien qu'un jour",
    "isCDO": true,
    "members": [
      1,
      4,
      5,
      8,
      9,
      10,
      11,
      12,
      16,
      17,
      19,
      20,
      21,
      22,
      23
    ],
    "guests": [
      "Raph"
    ]
  }
]
